autoupdate_languages/__init__.py
autoupdate_languages/core.py
autoupdate_languages-1.0.2.dist-info/licenses/LICENSE.txt
autoupdate_languages-1.0.2.dist-info/METADATA
autoupdate_languages-1.0.2.dist-info/WHEEL
autoupdate_languages-1.0.2.dist-info/entry_points.txt
autoupdate_languages-1.0.2.dist-info/top_level.txt
autoupdate_languages-1.0.2.dist-info/RECORD
